mkdocs_redirects/__init__.py
mkdocs_redirects/plugin.py
mkdocs_redirects-1.2.1.dist-info/LICENSE
mkdocs_redirects-1.2.1.dist-info/METADATA
mkdocs_redirects-1.2.1.dist-info/WHEEL
mkdocs_redirects-1.2.1.dist-info/entry_points.txt
mkdocs_redirects-1.2.1.dist-info/top_level.txt
mkdocs_redirects-1.2.1.dist-info/RECORD
