Metadata-Version: 2.1
Name: mkdocs-redirects
Version: 1.2.1
Summary: A MkDocs plugin for dynamic page redirects to prevent broken links.
Home-page: https://github.com/datarobot/mkdocs-redirects
Author: Dustin Burke
Author-email: dustin@datarobot.com
License: MIT
Keywords: mkdocs redirect
Classifier: Development Status :: 4 - Beta
Classifier: Intended Audience :: Developers
Classifier: Intended Audience :: Information Technology
Classifier: License :: OSI Approved :: MIT License
Classifier: Programming Language :: Python
Classifier: Programming Language :: Python :: 3
Classifier: Programming Language :: Python :: 3.6
Classifier: Programming Language :: Python :: 3.7
Classifier: Programming Language :: Python :: 3.8
Classifier: Programming Language :: Python :: 3.9
Classifier: Programming Language :: Python :: 3.10
Requires-Python: >=3.6
Provides-Extra: dev
Provides-Extra: test
Provides-Extra: release
License-File: LICENSE
